splunk_handler/__init__.py
splunk_handler-3.0.0.dist-info/LICENSE
splunk_handler-3.0.0.dist-info/METADATA
splunk_handler-3.0.0.dist-info/WHEEL
splunk_handler-3.0.0.dist-info/top_level.txt
splunk_handler-3.0.0.dist-info/RECORD
