Metadata-Version: 2.1
Name: splunk-handler
Version: 3.0.0
Summary: A Python logging handler that sends your logs to Splunk
Home-page: https://github.com/zach-taylor/splunk_handler
Author: Zach Taylor
Author-email: ztaylor234@gmail.com
License: MIT License
Platform: UNKNOWN
Classifier: Development Status :: 4 - Beta
Classifier: Intended Audience :: Developers
Classifier: License :: OSI Approved :: MIT License
Classifier: Natural Language :: English
Classifier: Operating System :: POSIX :: Linux
Classifier: Operating System :: MacOS :: MacOS X
Classifier: Programming Language :: Python
Classifier: Programming Language :: Python :: 3.6
Classifier: Programming Language :: Python :: 3.7
Classifier: Programming Language :: Python :: 3.8
Classifier: Programming Language :: Python :: 3.9
Classifier: Topic :: System :: Logging
License-File: LICENSE
